djangocopy/__init__.py
djangocopy/admin.py
djangocopy/apps.py
djangocopy/middleware.py
djangocopy/models.py
djangocopy/urls.py
djangocopy/utils.py
djangocopy/views.py
djangocopy/migrations/0001_initial.py
djangocopy/migrations/0002_historicalcopy_historicalnavbar_historicalpage.py
djangocopy/migrations/0003_auto_20190806_1308.py
djangocopy/migrations/0004_auto_20190807_2329.py
djangocopy/migrations/0005_auto_20190807_2333.py
djangocopy/migrations/0006_auto_20190810_1524.py
djangocopy/migrations/__init__.py
djangocopy/static/css/bootstrap-grid.min.css
djangocopy/static/css/bootstrap-grid.min.css.map
djangocopy/static/css/bootstrap-reboot.min.css
djangocopy/static/css/bootstrap-reboot.min.css.map
djangocopy/static/css/bootstrap.min.css
djangocopy/static/css/bootstrap.min.css.map
djangocopy/static/css/djangocopy.css
djangocopy/static/css/font-awesome.min.css
djangocopy/static/fonts/FontAwesome.otf
djangocopy/static/fonts/fontawesome-webfont.eot
djangocopy/static/fonts/fontawesome-webfont.svg
djangocopy/static/fonts/fontawesome-webfont.ttf
djangocopy/static/fonts/fontawesome-webfont.woff
djangocopy/static/fonts/fontawesome-webfont.woff2
djangocopy/static/js/bootstrap.bundle.min.js
djangocopy/static/js/bootstrap.bundle.min.js.map
djangocopy/static/js/bootstrap.min.js
djangocopy/static/js/bootstrap.min.js.map
djangocopy/static/js/cbpAnimatedHeader.js
djangocopy/static/js/djangocopy.js
djangocopy/static/js/html5shiv.min.js
djangocopy/static/js/jquery-3.3.1.min.js
djangocopy/static/js/jquery.cookiebar.js
djangocopy/static/js/popper.min.js
djangocopy/static/js/respond.min.js
djangocopy/static/js/wearprotection.js
djangocopy/templates/400.html
djangocopy/templates/403.html
djangocopy/templates/404.html
djangocopy/templates/500.html
djangocopy/templates/djangocopy/base.html
djangocopy/templates/djangocopy/default.html
djangocopy/templates/djangocopy/footer.html
djangocopy/templates/djangocopy/messages.html
djangocopy/templates/djangocopy/metadata.html
django_copy-0.1.0.dist-info/LICENSE
django_copy-0.1.0.dist-info/METADATA
django_copy-0.1.0.dist-info/WHEEL
django_copy-0.1.0.dist-info/top_level.txt
django_copy-0.1.0.dist-info/RECORD
