Metadata-Version: 2.1
Name: django-copy
Version: 0.1.0
Summary: Probably the smallest and simplest CMS for the Django framework
Home-page: https://github.com/ptav/django-copy
Author: Pedro Tavares
Author-email: web@ptavares.com
License: LICENSE
Keywords: Django,CMS
Platform: UNKNOWN
Classifier: Programming Language :: Python
Classifier: Topic :: Software Development :: Libraries :: Python Modules
Classifier: Framework :: Django
Classifier: Environment :: Web Environment
Classifier: Development Status :: 4 - Beta
Classifier: Programming Language :: Python
Classifier: Programming Language :: Python :: 3.6
License-File: LICENSE
